tb_device_mqtt.py
ex1/__init__.py
ex1/requirements.txt
ex1/tb_device_mqtt.py
ex1/tb_gateway_mqtt.py
392304jk324nkkl-0.0.0.dist-info/AUTHORS.rst
392304jk324nkkl-0.0.0.dist-info/LICENSE
392304jk324nkkl-0.0.0.dist-info/METADATA
392304jk324nkkl-0.0.0.dist-info/WHEEL
392304jk324nkkl-0.0.0.dist-info/top_level.txt
392304jk324nkkl-0.0.0.dist-info/RECORD
