Metadata-Version: 2.1
Name: 392304jk324nkkl
Version: 0.0.0
Summary: An example package. Generated with cookiecutter-pylibrary.
Home-page: https://github.com/serhiilikh/python-ex1
Author: Serhii Likhouzov
Author-email: serhii.likh@gmail.com
License: BSD 2-Clause License
Project-URL: Changelog, https://github.com/serhiilikh/python-ex1/blob/master/CHANGELOG.rst
Project-URL: Issue Tracker, https://github.com/serhiilikh/python-ex1/issues
Platform: UNKNOWN
Classifier: Development Status :: 5 - Production/Stable
Classifier: Intended Audience :: Developers
Classifier: License :: OSI Approved :: BSD License
Classifier: Operating System :: Unix
Classifier: Operating System :: POSIX
Classifier: Operating System :: Microsoft :: Windows
Classifier: Programming Language :: Python
Classifier: Programming Language :: Python :: 2.7
Classifier: Programming Language :: Python :: 3
Classifier: Programming Language :: Python :: 3.4
Classifier: Programming Language :: Python :: 3.5
Classifier: Programming Language :: Python :: 3.6
Classifier: Programming Language :: Python :: 3.7
Classifier: Programming Language :: Python :: Implementation :: CPython
Classifier: Programming Language :: Python :: Implementation :: PyPy
Classifier: Topic :: Utilities
Requires-Python: >=2.7, !=3.0.*, !=3.1.*, !=3.2.*, !=3.3.*
Requires-Dist: jsonschema (>=3.0.1)
Requires-Dist: paho-mqtt (==1.4.0)
